opentelemetry/launcher/__init__.py
opentelemetry/launcher/_metrics_exporter.py
opentelemetry/launcher/configuration.py
opentelemetry/launcher/tracer.py
opentelemetry/launcher/version.py
opentelemetry_launcher-1.16.0.dist-info/LICENSE
opentelemetry_launcher-1.16.0.dist-info/METADATA
opentelemetry_launcher-1.16.0.dist-info/WHEEL
opentelemetry_launcher-1.16.0.dist-info/entry_points.txt
opentelemetry_launcher-1.16.0.dist-info/top_level.txt
opentelemetry_launcher-1.16.0.dist-info/RECORD
