Metadata-Version: 2.1
Name: opentelemetry-launcher
Version: 1.16.0
Summary: Launcher, Configuration Layer for OpenTelemetry
Home-page: https://github.com/lightstep/otel-launcher-python
Author: Lightstep Authors
License: Apache-2.0
Platform: any
Classifier: Development Status :: 4 - Beta
Classifier: Intended Audience :: Developers
Classifier: License :: OSI Approved :: Apache Software License
Classifier: Programming Language :: Python
Classifier: Programming Language :: Python :: 3
Classifier: Programming Language :: Python :: 3.7
Classifier: Programming Language :: Python :: 3.8
Classifier: Programming Language :: Python :: 3.9
Classifier: Programming Language :: Python :: 3.10
Requires-Python: >=3.7
License-File: LICENSE
Requires-Dist: environs >=8.0.0
Requires-Dist: opentelemetry-api ==1.20.0
Requires-Dist: opentelemetry-sdk ==1.20.0
Requires-Dist: opentelemetry-exporter-otlp ==1.20.0
Requires-Dist: opentelemetry-propagator-b3 ==1.20.0
Requires-Dist: opentelemetry-instrumentation ==0.41b0
Provides-Extra: test
Requires-Dist: httpretty ~=1.0.2 ; extra == 'test'
